{"version":"2026.07.06.22","publishedAt":"2026-07-06T10:54:51Z","sha256":"746b43ea104767a6e95a945d33616c098bdcf2caec72ad77742a870e4b71ced5","notes":"Исправлена статистика по среднему: разряд теперь засчитывается в строки 7/6/5. Синхронизация переделана: сохранение считается успешным только после проверки свежей ревизии на Supabase, автосохранение сначала читает сервер, объединяет данные и потом записывает.","name":"Табель рабочих мест.apk","apkUrl":"https://raw.githubusercontent.com/Sasha174ru/tabel-workplaces-updates/main/default.apk"}